odoo/addons/ai_oca_bridge_crm_lead/README.rst
odoo/addons/ai_oca_bridge_crm_lead/__init__.py
odoo/addons/ai_oca_bridge_crm_lead/__manifest__.py
odoo/addons/ai_oca_bridge_crm_lead/demo/ai_bridge_demo.xml
odoo/addons/ai_oca_bridge_crm_lead/i18n/ai_oca_bridge_crm_lead.pot
odoo/addons/ai_oca_bridge_crm_lead/i18n/it.po
odoo/addons/ai_oca_bridge_crm_lead/models/__init__.py
odoo/addons/ai_oca_bridge_crm_lead/models/crm_lead.py
odoo/addons/ai_oca_bridge_crm_lead/readme/CONFIGURE.md
odoo/addons/ai_oca_bridge_crm_lead/readme/CONTRIBUTORS.md
odoo/addons/ai_oca_bridge_crm_lead/readme/DESCRIPTION.md
odoo/addons/ai_oca_bridge_crm_lead/readme/USAGE.md
odoo/addons/ai_oca_bridge_crm_lead/static/description/icon.png
odoo/addons/ai_oca_bridge_crm_lead/static/description/index.html
odoo/addons/ai_oca_bridge_crm_lead/tests/__init__.py
odoo/addons/ai_oca_bridge_crm_lead/tests/test_crm_lead_ai_bridge.py
odoo_addon_ai_oca_bridge_crm_lead-16.0.2.0.0.dist-info/METADATA
odoo_addon_ai_oca_bridge_crm_lead-16.0.2.0.0.dist-info/WHEEL
odoo_addon_ai_oca_bridge_crm_lead-16.0.2.0.0.dist-info/top_level.txt
odoo_addon_ai_oca_bridge_crm_lead-16.0.2.0.0.dist-info/RECORD
